zodiac_sign.py
zodiac_sign-0.2.5.dist-info/LICENSE
zodiac_sign-0.2.5.dist-info/METADATA
zodiac_sign-0.2.5.dist-info/WHEEL
zodiac_sign-0.2.5.dist-info/top_level.txt
zodiac_sign-0.2.5.dist-info/RECORD
